taskw_gcal_sync/GCalSide.py
taskw_gcal_sync/GenericSide.py
taskw_gcal_sync/PrefsManager.py
taskw_gcal_sync/TWGCalAggregator.py
taskw_gcal_sync/TaskWarriorSide.py
taskw_gcal_sync/__init__.py
taskw_gcal_sync/helpers.py
taskw_gcal_sync/logger.py
taskw_gcal_sync/res/gcal_client_secret.json
taskw_gcal_sync/scripts/tw_gcal_sync.py
taskw_gcal_sync/scripts/tw_gcal_sync.py.backup
taskw_gcal_sync-1.0.2.dist-info/entry_points.txt
taskw_gcal_sync-1.0.2.dist-info/LICENSE
taskw_gcal_sync-1.0.2.dist-info/WHEEL
taskw_gcal_sync-1.0.2.dist-info/METADATA
taskw_gcal_sync-1.0.2.dist-info/RECORD
