Metadata-Version: 2.1
Name: taskw-gcal-sync
Version: 1.0.2
Summary: Taskwarrior <-> Google Calendar synchronisation tool
Home-page: https://github.com/bergercookie/taskw_gcal_sync
License: MIT
Author: Nikos Koukis
Author-email: nickkouk@gmail.com
Requires-Python: >=3.8,<4.0
Classifier: Development Status :: 7 - Inactive
Classifier: License :: OSI Approved :: MIT License
Classifier: Programming Language :: Python :: 3
Classifier: Programming Language :: Python :: 3.10
Classifier: Programming Language :: Python :: 3.8
Classifier: Programming Language :: Python :: 3.9
Requires-Dist: taskwarrior-syncall[gcal] (>=1.1.0,<2.0.0)
Project-URL: Repository, https://github.com/bergercookie/taskw_gcal_sync
